httpx_caching/__init__.py
httpx_caching/__version__.py
httpx_caching/_heuristics.py
httpx_caching/_models.py
httpx_caching/_policy.py
httpx_caching/_serializer.py
httpx_caching/_types.py
httpx_caching/_utils.py
httpx_caching/_wrapper.py
httpx_caching/py.typed
httpx_caching/_async/__init__.py
httpx_caching/_async/_cache.py
httpx_caching/_async/_transport.py
httpx_caching/_sync/__init__.py
httpx_caching/_sync/_cache.py
httpx_caching/_sync/_transport.py
httpx_caching-0.1a4.dist-info/METADATA
httpx_caching-0.1a4.dist-info/WHEEL
httpx_caching-0.1a4.dist-info/top_level.txt
httpx_caching-0.1a4.dist-info/RECORD
