Metadata-Version: 2.1
Name: httpx-caching
Version: 0.1a4
Summary: Caching for HTTPX.
Home-page: https://github.com/johtso/httpx-caching
Author: Johannes (johtso)
Author-email: johtso@gmail.com
License: Apache-2.0
Project-URL: Source, https://github.com/johtso/httpx-caching
Platform: UNKNOWN
Classifier: Development Status :: 3 - Alpha
Classifier: Environment :: Web Environment
Classifier: Intended Audience :: Developers
Classifier: License :: OSI Approved :: Apache Software License
Classifier: Operating System :: OS Independent
Classifier: Topic :: Internet :: WWW/HTTP
Classifier: Programming Language :: Python :: 3
Classifier: Programming Language :: Python :: 3.7
Classifier: Programming Language :: Python :: 3.8
Classifier: Programming Language :: Python :: 3.9
Classifier: Programming Language :: Python :: 3.10
Classifier: Programming Language :: Python :: 3 :: Only
Requires-Python: >=3.7
Requires-Dist: httpx (>=0.22.0)
Requires-Dist: msgpack
Requires-Dist: anyio
Requires-Dist: multimethod
